brynq_sdk_mysql/__init__.py
brynq_sdk_mysql/mysql.py
brynq_sdk_mysql-3.0.4.dist-info/METADATA
brynq_sdk_mysql-3.0.4.dist-info/WHEEL
brynq_sdk_mysql-3.0.4.dist-info/top_level.txt
brynq_sdk_mysql-3.0.4.dist-info/RECORD
