Metadata-Version: 2.4
Name: brynq_sdk_mysql
Version: 3.0.4
Summary: MySQL wrapper from Bryn
Author: BrynQ
Author-email: support@brynq.com
License: BrynQ License
Requires-Dist: brynq-sdk-brynq<5,>=4
Requires-Dist: pandas<3,>=1
Requires-Dist: pymysql<=2,>=1
Requires-Dist: requests<=3,>=2
Requires-Dist: cryptography<=38,>=38
Dynamic: author
Dynamic: author-email
Dynamic: description
Dynamic: license
Dynamic: requires-dist
Dynamic: summary
